setup.py
slackclient/__init__.py
slackclient/_channel.py
slackclient/_client.py
slackclient/_im.py
slackclient/_server.py
slackclient/_slackrequest.py
slackclient/_user.py
slackclient/_util.py
thieman_slackclient.egg-info/PKG-INFO
thieman_slackclient.egg-info/SOURCES.txt
thieman_slackclient.egg-info/dependency_links.txt
thieman_slackclient.egg-info/not-zip-safe
thieman_slackclient.egg-info/requires.txt
thieman_slackclient.egg-info/top_level.txt