Metadata-Version: 1.0
Name: thieman-slackclient
Version: 0.16.1
Summary: Python client for Slack.com
Home-page: http://github.com/slackhq/python-slackclient
Author: Ryan Huber
Author-email: ryan@slack-corp.com
License: MIT
Platform: UNKNOWN
